codepulse/TrackerClass.py
codepulse/__init__.py
codepulse/utils.py
codepulse-0.1.0.dist-info/LICENSE
codepulse-0.1.0.dist-info/METADATA
codepulse-0.1.0.dist-info/WHEEL
codepulse-0.1.0.dist-info/top_level.txt
codepulse-0.1.0.dist-info/RECORD
