Metadata-Version: 2.1
Name: codepulse
Version: 0.1.0
Summary: Measure execution time for each line of a function.
Home-page: https://github.com/codepulse-developers/codepulse
Author: codepulse
Author-email: codepulsedevelopers@gmail.com
Classifier: Programming Language :: Python :: 3
Classifier: License :: OSI Approved :: MIT License
Classifier: Operating System :: OS Independent
Requires-Python: >=3.6
License-File: LICENSE
Requires-Dist: pandas
